zhihu_md/__info__.py
zhihu_md/__init__.py
zhihu_md/__main__.py
zhihu_md/main.py
zhihu_md-0.1.1.dist-info/METADATA
zhihu_md-0.1.1.dist-info/WHEEL
zhihu_md-0.1.1.dist-info/entry_points.txt
zhihu_md-0.1.1.dist-info/top_level.txt
zhihu_md-0.1.1.dist-info/RECORD
