Metadata-Version: 2.4
Name: zhihu_md
Version: 0.1.1
Summary: 把 markdown 转换为知乎能正常导入的 markdown。支持自动处理图片、公式
Author-email: DIYer22 <ylxx@live.com>
Maintainer-email: DIYer22 <ylxx@live.com>
License: MIT
Project-URL: Homepage, https://github.com/DIYer22/zhihu_md
Project-URL: Repository, https://github.com/DIYer22/zhihu_md
Project-URL: Issues, https://github.com/DIYer22/zhihu_md/issues
Keywords: zhihu_md
Classifier: Topic :: Software Development :: Libraries :: Python Modules
Classifier: Programming Language :: Python :: 3
Classifier: Operating System :: OS Independent
Requires-Python: >=3.7
Requires-Dist: chardet
Requires-Dist: Pillow
Provides-Extra: dev
Requires-Dist: pytest>=7.0; extra == "dev"
Requires-Dist: pytest-cov>=4.0; extra == "dev"
Requires-Dist: black>=22.0; extra == "dev"
Requires-Dist: isort>=5.0; extra == "dev"
Requires-Dist: flake8>=5.0; extra == "dev"
Requires-Dist: mypy>=1.0; extra == "dev"
